{
	"animations": [
		{
			"loop": false,
			"offsets": [
				0,
				0
			],
			"anim": "idle",
			"fps": 24,
			"name": "bf idle",
			"indices": []
		},
		{
			"loop": false,
			"offsets": [
				-13,
				-13
			],
			"anim": "singLEFT",
			"fps": 24,
			"name": "bf left",
			"indices": []
		},
		{
			"loop": false,
			"offsets": [
				-20,
				-51
			],
			"anim": "singDOWN",
			"fps": 24,
			"name": "bf down",
			"indices": []
		},
		{
			"loop": false,
			"offsets": [
				-32,
				17
			],
			"anim": "singUP",
			"fps": 24,
			"name": "bf up",
			"indices": []
		},
		{
			"loop": false,
			"offsets": [
				-33,
				-4
			],
			"anim": "singRIGHT",
			"fps": 24,
			"name": "bf right",
			"indices": []
		}
	],
	"vocals_file": "bf-classic",
	"no_antialiasing": false,
	"image": "characters/bf/bf-modern",
	"position": [
		0,
		300
	],
	"healthicon": "bf-modern",
	"flip_x": true,
	"healthbar_colors": [
		49,
		176,
		209
	],
	"camera_position": [
		20,
		30
	],
	"sing_duration": 4,
	"scale": 0.97
}